{"Cards":[{ "Cost":7,"Attack":10,"Defense":2,"HasTaunt":false,"HasTrample":false,"HasDistortion":false,"HasFirstStrike":true }, { "Cost":4,"Attack":1,"Defense":5,"HasTaunt":false,"HasTrample":false,"HasDistortion":true,"HasFirstStrike":false }, { "Cost":5,"Attack":7,"Defense":1,"HasTaunt":false,"HasTrample":false,"HasDistortion":true,"HasFirstStrike":false }, { "Cost":7,"Attack":1,"Defense":9,"HasTaunt":false,"HasTrample":false,"HasDistortion":true,"HasFirstStrike":true }, { "Cost":7,"Attack":5,"Defense":5,"HasTaunt":false,"HasTrample":true,"HasDistortion":true,"HasFirstStrike":false }, { "Cost":7,"Attack":8,"Defense":2,"HasTaunt":false,"HasTrample":true,"HasDistortion":false,"HasFirstStrike":true }, { "Cost":7,"Attack":8,"Defense":1,"HasTaunt":true,"HasTrample":true,"HasDistortion":false,"HasFirstStrike":false }, { "Cost":4,"Attack":1,"Defense":2,"HasTaunt":true,"HasTrample":false,"HasDistortion":true,"HasFirstStrike":false }, { "Cost":6,"Attack":2,"Defense":7,"HasTaunt":false,"HasTrample":false,"HasDistortion":false,"HasFirstStrike":true }, { "Cost":3,"Attack":0,"Defense":3,"HasTaunt":false,"HasTrample":true,"HasDistortion":false,"HasFirstStrike":false }, { "Cost":3,"Attack":4,"Defense":2,"HasTaunt":false,"HasTrample":false,"HasDistortion":false,"HasFirstStrike":false }, { "Cost":7,"Attack":3,"Defense":8,"HasTaunt":false,"HasTrample":true,"HasDistortion":false,"HasFirstStrike":false }, { "Cost":5,"Attack":8,"Defense":1,"HasTaunt":false,"HasTrample":false,"HasDistortion":false,"HasFirstStrike":false }, { "Cost":5,"Attack":6,"Defense":2,"HasTaunt":false,"HasTrample":false,"HasDistortion":false,"HasFirstStrike":true }, { "Cost":5,"Attack":1,"Defense":5,"HasTaunt":false,"HasTrample":true,"HasDistortion":true,"HasFirstStrike":false }, { "Cost":7,"Attack":2,"Defense":3,"HasTaunt":true,"HasTrample":true,"HasDistortion":true,"HasFirstStrike":true }, { "Cost":7,"Attack":9,"Defense":1,"HasTaunt":true,"HasTrample":false,"HasDistortion":false,"HasFirstStrike":false }, { "Cost":6,"Attack":6,"Defense":1,"HasTaunt":false,"HasTrample":true,"HasDistortion":true,"HasFirstStrike":false }, { "Cost":4,"Attack":3,"Defense":4,"HasTaunt":false,"HasTrample":false,"HasDistortion":false,"HasFirstStrike":false }, { "Cost":8,"Attack":7,"Defense":7,"HasTaunt":false,"HasTrample":false,"HasDistortion":false,"HasFirstStrike":true }, { "Cost":7,"Attack":5,"Defense":2,"HasTaunt":false,"HasTrample":true,"HasDistortion":true,"HasFirstStrike":true }, { "Cost":3,"Attack":5,"Defense":1,"HasTaunt":false,"HasTrample":false,"HasDistortion":false,"HasFirstStrike":false }, { "Cost":4,"Attack":6,"Defense":1,"HasTaunt":false,"HasTrample":false,"HasDistortion":false,"HasFirstStrike":false }, { "Cost":8,"Attack":9,"Defense":5,"HasTaunt":false,"HasTrample":false,"HasDistortion":false,"HasFirstStrike":true }, { "Cost":5,"Attack":3,"Defense":4,"HasTaunt":false,"HasTrample":false,"HasDistortion":false,"HasFirstStrike":true }, { "Cost":6,"Attack":3,"Defense":7,"HasTaunt":false,"HasTrample":true,"HasDistortion":false,"HasFirstStrike":false }, { "Cost":6,"Attack":7,"Defense":2,"HasTaunt":false,"HasTrample":false,"HasDistortion":false,"HasFirstStrike":true }, { "Cost":4,"Attack":3,"Defense":1,"HasTaunt":false,"HasTrample":true,"HasDistortion":true,"HasFirstStrike":false }, { "Cost":2,"Attack":0,"Defense":3,"HasTaunt":false,"HasTrample":false,"HasDistortion":false,"HasFirstStrike":false }, { "Cost":8,"Attack":8,"Defense":4,"HasTaunt":false,"HasTrample":true,"HasDistortion":true,"HasFirstStrike":false }]}